lauft.py
lauft-1.0.dist-info/METADATA
lauft-1.0.dist-info/WHEEL
lauft-1.0.dist-info/entry_points.txt
lauft-1.0.dist-info/top_level.txt
lauft-1.0.dist-info/RECORD
