Metadata-Version: 2.1
Name: lauft
Version: 1.0
Summary: Availabilty Check
Home-page: UNKNOWN
Author: UNKNOWN
Author-email: git@unstable.ch
License: UNKNOWN
Platform: UNKNOWN
Requires-Dist: requests
